uncert/__init__.py
uncert/_common.py
uncert/_derivative_table.py
uncert/measurement.py
uncert/measurement.pyi
uncert/uncertainty.py
uncert/uncertainty.pyi
uncert-0.2.0.dist-info/METADATA
uncert-0.2.0.dist-info/WHEEL
uncert-0.2.0.dist-info/top_level.txt
uncert-0.2.0.dist-info/RECORD
